fiftyone/brain/__init__.py
fiftyone/brain/config.py
fiftyone/brain/similarity.py
fiftyone/brain/visualization.py
fiftyone/brain/internal/__init__.py
fiftyone/brain/internal/core/__init__.py
fiftyone/brain/internal/core/duplicates.py
fiftyone/brain/internal/core/elasticsearch.py
fiftyone/brain/internal/core/hardness.py
fiftyone/brain/internal/core/lancedb.py
fiftyone/brain/internal/core/leaky_splits.py
fiftyone/brain/internal/core/milvus.py
fiftyone/brain/internal/core/mistakenness.py
fiftyone/brain/internal/core/mongodb.py
fiftyone/brain/internal/core/mosaic.py
fiftyone/brain/internal/core/pgvector.py
fiftyone/brain/internal/core/pinecone.py
fiftyone/brain/internal/core/qdrant.py
fiftyone/brain/internal/core/redis.py
fiftyone/brain/internal/core/representativeness.py
fiftyone/brain/internal/core/sklearn.py
fiftyone/brain/internal/core/uniqueness.py
fiftyone/brain/internal/core/utils.py
fiftyone/brain/internal/core/visualization.py
fiftyone/brain/internal/models/.gitignore
fiftyone/brain/internal/models/__init__.py
fiftyone/brain/internal/models/manifest.json
fiftyone/brain/internal/models/simple_resnet.py
fiftyone/brain/internal/models/torch.py
fiftyone_brain-0.21.5.dist-info/licenses/LICENSE
fiftyone_brain-0.21.5.dist-info/METADATA
fiftyone_brain-0.21.5.dist-info/WHEEL
fiftyone_brain-0.21.5.dist-info/top_level.txt
fiftyone_brain-0.21.5.dist-info/RECORD
